comparator_n.vhd
--
-- AAD 2025/2026, n-bit comparator
--
-- for extra credit, implement this also using chains of unsigned comparators:
--
-- unsigned comparator stage (one per bit)
--   in   a_bit   b_bit   old_lt   old_eq   old_gt
--   out                  new_lt   new_eq   new_gt
-- logic, start from the least significant bit with old_lt=old_gt=0 and old_eq=1
--   if a_bit=b_bit (no change, keep the earlier result)
--     new_lt=old_lt   new_eq=old_eq   new_gt=old_gt
--   else if a_bit=1 (a is greater because a_bit=1 and b_bit=0)
--     new_lt=0        new_eq=0        new_gt=1
--   else  (a is smaller because a_bit=0 and b_bit=1)
--     new_lt=1        new_eq=0        new_gt=0
-- use a transport delay of 5 ps per stage
--

library IEEE;
use IEEE.std_logic_1164.all;
use IEEE.numeric_std.all;

entity comparator_n is
  generic ( N : integer := 4 );
  port (
    a, b : in  std_logic_vector(N-1 downto 0);
    lt   : out std_logic;
    eq   : out std_logic;
    gt   : out std_logic  -- Adicionado para resolver o erro do TB
  );
end comparator_n;

architecture behavioral of comparator_n is
  signal s_lt, s_eq, s_gt : std_logic_vector(N downto 0);
begin
  -- Condições iniciais no MSB (bit N)
  s_lt(N) <= '0';
  s_eq(N) <= '1';
  s_gt(N) <= '0';

  gen_comp: for i in N-1 downto 0 generate
    -- Lógica com atraso de transporte de 5ps conforme enunciado
    s_lt(i) <= (s_lt(i+1) or (s_eq(i+1) and (not a(i) and b(i)))) after 5 ps;
    s_eq(i) <= (s_eq(i+1) and (a(i) xnor b(i))) after 5 ps;
    s_gt(i) <= (s_gt(i+1) or (s_eq(i+1) and (a(i) and not b(i)))) after 5 ps;
  end generate;

  lt <= s_lt(0);
  eq <= s_eq(0);
  gt <= s_gt(0);
end behavioral;

comparator_n_tb.vhd
--
-- AAD 2025/2026, comparator testbench
--

library IEEE;
use IEEE.std_logic_1164.all;
use IEEE.numeric_std.all;

entity comparator_n_tb is
end comparator_n_tb;

architecture stimulus of comparator_n_tb is
  -- constants
  constant N : positive := 4;
  -- the interface signals
  signal s_a  : std_logic_vector(N-1 downto 0);
  signal s_b  : std_logic_vector(N-1 downto 0);
  signal s_lt : std_logic;
  signal s_eq : std_logic;
  signal s_gt : std_logic;
begin
  uut : entity work.comparator_n(behavioral)
               generic map
               (
                 N => N
               )
               port map
               (
                 a  => s_a,
                 b  => s_b,
                 lt => s_lt,
                 eq => s_eq,
                 gt => s_gt
               );
  stim : process is
  begin
    s_a <= "0010";
    s_b <= "0010";
    wait for 200 ps;
    s_a <= "1011";
    s_b <= "0100";
    wait for 200 ps;
    s_a <= "0101";
    s_b <= "1010";
    wait for 200 ps;
    s_a <= "0111";
    s_b <= "0111";
    wait for 200 ps;
    s_a <= "1111";
    s_b <= "1110";
    wait for 200 ps;
    s_a <= "0110";
    s_b <= "1101";
    wait for 200 ps;
    s_a <= "1000";
    s_b <= "0110";
    wait for 200 ps;
    wait;
  end process;
end stimulus;

comparator_n.vcd
$date
  Tue Jan 13 16:34:07 2026
$end
$version
  GHDL v0
$end
$timescale
  1 fs
$end
$scope module standard $end
$upscope $end
$scope module textio $end
$upscope $end
$scope module std_logic_1164 $end
$upscope $end
$scope module numeric_std $end
$upscope $end
$scope module comparator_n_tb $end
$var reg 4 ! s_a[3:0] $end
$var reg 4 " s_b[3:0] $end
$var reg 1 # s_lt $end
$var reg 1 $ s_eq $end
$var reg 1 % s_gt $end
$scope module uut $end
$var reg 4 & a[3:0] $end
$var reg 4 ' b[3:0] $end
$var reg 1 ( lt $end
$var reg 1 ) eq $end
$var reg 1 * gt $end
$var reg 5 + s_lt[4:0] $end
$var reg 5 , s_eq[4:0] $end
$var reg 5 - s_gt[4:0] $end
$scope module gen_comp(0) $end
$upscope $end
$scope module gen_comp(1) $end
$upscope $end
$scope module gen_comp(2) $end
$upscope $end
$scope module gen_comp(3) $end
$upscope $end
$upscope $end
$upscope $end
$enddefinitions $end
#0
b0010 !
b0010 "
U#
U$
U%
b0010 &
b0010 '
U(
U)
U*
b0UUUU +
b1UUUU ,
b0UUUU -
#5000
b00UUU +
b11UUU ,
b00UUU -
#10000
b000UU +
b111UU ,
b000UU -
#15000
b0000U +
b1111U ,
b0000U -
#20000
0#
1$
0%
0(
1)
0*
b00000 +
b11111 ,
b00000 -
#200000
b1011 !
b0100 "
b1011 &
b0100 '
#205000
0$
1%
0)
1*
b00100 +
b10000 ,
b01011 -
#210000
b00010 +
b01101 -
#215000
1#
0%
1(
0*
b00001 +
b01110 -
#220000
0#
1%
0(
1*
b00000 +
b01111 -
#400000
b0101 !
b1010 "
b0101 &
b1010 '
#405000
b01000 +
b00111 -
#410000
b01100 +
b00011 -
#415000
b01110 +
b00001 -
#420000
1#
0%
1(
0*
b01111 +
b00000 -
#600000
b0111 !
b0111 "
b0111 &
b0111 '
#605000
b00111 +
b11000 ,
#610000
b00011 +
b11100 ,
#615000
b00001 +
b11110 ,
#620000
0#
1$
0(
1)
b00000 +
b11111 ,
#800000
b1111 !
b1110 "
b1111 &
b1110 '
#805000
0$
1%
0)
1*
b11110 ,
b00001 -
