comparator_n.vhd
--
-- AAD 2025/2026, n-bit comparator
--
-- for extra credit, implement this also using chains of unsigned comparators:
--
-- unsigned comparator stage (one per bit)
--   in   a_bit   b_bit   old_lt   old_eq   old_gt
--   out                  new_lt   new_eq   new_gt
-- logic, start from the least significant bit with old_lt=old_gt=0 and old_eq=1
--   if a_bit=b_bit (no change, keep the earlier result)
--     new_lt=old_lt   new_eq=old_eq   new_gt=old_gt
--   else if a_bit=1 (a is greater because a_bit=1 and b_bit=0)
--     new_lt=0        new_eq=0        new_gt=1
--   else  (a is smaller because a_bit=0 and b_bit=1)
--     new_lt=1        new_eq=0        new_gt=0
-- use a transport delay of 5 ps per stage
--

library IEEE;
use IEEE.std_logic_1164.all;
use IEEE.numeric_std.all;

entity comparator_n is
  generic ( N : integer := 4 );
  port (
    a, b : in  std_logic_vector(N-1 downto 0);
    lt   : out std_logic;
    eq   : out std_logic;
    gt   : out std_logic  -- Adicionado para resolver o erro do TB
  );
end comparator_n;

architecture behavioral of comparator_n is
  signal s_lt, s_eq, s_gt : std_logic_vector(N downto 0);
begin
  -- Condições iniciais no LSB (bit 0)
  s_lt(0) <= '0';
  s_eq(0) <= '1';
  s_gt(0) <= '0';

  gen_comp: for i in 0 to N-1 generate
    -- Lógica com atraso de transporte de 5ps conforme enunciado
    s_lt(i+1) <= (s_lt(i) or (s_eq(i) and (not a(i) and b(i)))) after 5 ps;
    s_eq(i+1) <= (s_eq(i) and (a(i) xnor b(i))) after 5 ps;
    s_gt(i+1) <= (s_gt(i) or (s_eq(i) and (a(i) and not b(i)))) after 5 ps;
  end generate;

  lt <= s_lt(N);
  eq <= s_eq(N);
  gt <= s_gt(N);
end behavioral;

comparator_n_tb.vhd
--
-- AAD 2025/2026, comparator testbench
--

library IEEE;
use IEEE.std_logic_1164.all;
use IEEE.numeric_std.all;

entity comparator_n_tb is
end comparator_n_tb;

architecture stimulus of comparator_n_tb is
  -- constants
  constant N : positive := 4;
  -- the interface signals
  signal s_a  : std_logic_vector(N-1 downto 0);
  signal s_b  : std_logic_vector(N-1 downto 0);
  signal s_lt : std_logic;
  signal s_eq : std_logic;
  signal s_gt : std_logic;
begin
  uut : entity work.comparator_n(behavioral)
               generic map
               (
                 N => N
               )
               port map
               (
                 a  => s_a,
                 b  => s_b,
                 lt => s_lt,
                 eq => s_eq,
                 gt => s_gt
               );
  stim : process is
  begin
    s_a <= "0010";
    s_b <= "0010";
    wait for 200 ps;
    s_a <= "1011";
    s_b <= "0100";
    wait for 200 ps;
    s_a <= "0101";
    s_b <= "1010";
    wait for 200 ps;
    s_a <= "0111";
    s_b <= "0111";
    wait for 200 ps;
    s_a <= "1111";
    s_b <= "1110";
    wait for 200 ps;
    s_a <= "0110";
    s_b <= "1101";
    wait for 200 ps;
    s_a <= "1000";
    s_b <= "0110";
    wait for 200 ps;
    wait;
  end process;
end stimulus;

comparator_n.vcd
$date
  Thu Jan 15 16:58:42 2026
$end
$version
  GHDL v0
$end
$timescale
  1 fs
$end
$scope module standard $end
$upscope $end
$scope module textio $end
$upscope $end
$scope module std_logic_1164 $end
$upscope $end
$scope module numeric_std $end
$upscope $end
$scope module comparator_n_tb $end
$var reg 4 ! s_a[3:0] $end
$var reg 4 " s_b[3:0] $end
$var reg 1 # s_lt $end
$var reg 1 $ s_eq $end
$var reg 1 % s_gt $end
$scope module uut $end
$var reg 4 & a[3:0] $end
$var reg 4 ' b[3:0] $end
$var reg 1 ( lt $end
$var reg 1 ) eq $end
$var reg 1 * gt $end
$var reg 5 + s_lt[4:0] $end
$var reg 5 , s_eq[4:0] $end
$var reg 5 - s_gt[4:0] $end
$scope module gen_comp(0) $end
$upscope $end
$scope module gen_comp(1) $end
$upscope $end
$scope module gen_comp(2) $end
$upscope $end
$scope module gen_comp(3) $end
$upscope $end
$upscope $end
$upscope $end
$enddefinitions $end
#0
b0010 !
b0010 "
U#
U$
U%
b0010 &
b0010 '
U(
U)
U*
bUUUU0 +
bUUUU1 ,
bUUUU0 -
#5000
bUUU00 +
bUUU11 ,
bUUU00 -
#10000
bUU000 +
bUU111 ,
bUU000 -
#15000
bU0000 +
bU1111 ,
bU0000 -
#20000
0#
1$
0%
0(
1)
0*
b00000 +
b11111 ,
b00000 -
#200000
b1011 !
b0100 "
b1011 &
b0100 '
#205000
0$
1%
0)
1*
b01000 +
b00001 ,
b10110 -
#210000
1#
0%
1(
0*
b10000 +
b01110 -
#215000
0#
1%
0(
1*
b00000 +
b11110 -
#400000
b0101 !
b1010 "
b0101 &
b1010 '
#405000
#600000
b0111 !
b0111 "
b0111 &
b0111 '
#605000
b00011 ,
b11100 -
#610000
b00111 ,
b11000 -
#615000
b01111 ,
b10000 -
#620000
1$
0%
1)
0*
b11111 ,
b00000 -
#800000
b1111 !
b1110 "
b1111 &
b1110 '
#805000
b11101 ,
b00010 -
#810000
b11001 ,
b00110 -
#815000
b10001 ,
b01110 -
#820000
0$
1%
0)
1*
b00001 ,
b11110 -
#1000000
b0110 !
b1101 "
b0110 &
b1101 '
#1005000
b00010 +
b11100 -
#1010000
b00110 +
b11000 -
#1015000
b01110 +
b10000 -
#1020000
1#
0%
1(
0*
b11110 +
b00000 -
#1200000
b1000 !
b0110 "
b1000 &
b0110 '
#1205000
b11100 +
b00011 ,
